sharepoint_wrapper/__init__.py
sharepoint_wrapper/_constants.py
sharepoint_wrapper/_raw.py
sharepoint_wrapper-0.0.4.dist-info/METADATA
sharepoint_wrapper-0.0.4.dist-info/WHEEL
sharepoint_wrapper-0.0.4.dist-info/licenses/LICENSE
sharepoint_wrapper-0.0.4.dist-info/RECORD
