Metadata-Version: 2.4
Name: sharepoint_wrapper
Version: 0.0.4
Summary: A basic sharepoint wrapper to be used with app-only credentials
Project-URL: Homepage, https://github.com/ShyamPanchal/sharepoint_wrapper
Project-URL: Issues, https://github.com/ShyamPanchal/sharepoint_wrapper/issues
Author-email: Shyam Panchal <shyampanchal95@gmail.com>
License-File: LICENSE
Classifier: License :: OSI Approved :: MIT License
Classifier: Operating System :: OS Independent
Classifier: Programming Language :: Python :: 3
Requires-Python: >=3.8
